{"trial_id": "020", "hyperparameters": {"space": [{"class_name": "Int", "config": {"name": "units", "default": null, "conditions": [], "min_value": 100, "max_value": 256, "step": 32, "sampling": "linear"}}, {"class_name": "Float", "config": {"name": "dropout_rate", "default": 0.1, "conditions": [], "min_value": 0.1, "max_value": 0.3, "step": 0.1, "sampling": "linear"}}, {"class_name": "Float", "config": {"name": "learning_rate", "default": 1e-05, "conditions": [], "min_value": 1e-05, "max_value": 0.001, "step": null, "sampling": "log"}}], "values": {"units": 196, "dropout_rate": 0.1, "learning_rate": 0.00013407608528649104}}, "metrics": {"metrics": {"loss": {"direction": "min", "observations": [{"value": [0.004594721831381321], "step": 93}]}, "mae": {"direction": "min", "observations": [{"value": [0.04707455635070801], "step": 93}]}, "val_loss": {"direction": "min", "observations": [{"value": [0.005465890280902386], "step": 93}]}, "val_mae": {"direction": "min", "observations": [{"value": [0.04683015123009682], "step": 93}]}}}, "score": 0.005465890280902386, "best_step": 93, "status": "COMPLETED", "message": null}